xknxproject/__init__.py
xknxproject/__version__.py
xknxproject/const.py
xknxproject/py.typed
xknxproject/util.py
xknxproject/xknxproj.py
xknxproject/combination/__init__.py
xknxproject/combination/combination.py
xknxproject/exceptions/__init__.py
xknxproject/exceptions/exceptions.py
xknxproject/loader/__init__.py
xknxproject/loader/application_program_loader.py
xknxproject/loader/hardware_loader.py
xknxproject/loader/knx_master_loader.py
xknxproject/loader/project_loader.py
xknxproject/models/__init__.py
xknxproject/models/knxproject.py
xknxproject/models/models.py
xknxproject/models/static.py
xknxproject/xml/__init__.py
xknxproject/xml/parser.py
xknxproject/zip/__init__.py
xknxproject/zip/extractor.py
xknxproject-3.8.2.dist-info/LICENSE
xknxproject-3.8.2.dist-info/METADATA
xknxproject-3.8.2.dist-info/WHEEL
xknxproject-3.8.2.dist-info/top_level.txt
xknxproject-3.8.2.dist-info/RECORD
