Metadata-Version: 2.2
Name: xknxproject
Version: 3.8.2
Summary: A library to gather information from ETS project files used for KNX
Author-email: Marvin Wichmann <me@marvin-wichmann.de>, Matthias Alphart <farmio@alphart.net>
License: GPL-2.0-only
Project-URL: homepage, https://github.com/XKNX/xknxproject
Keywords: KNX,ETS,Home Assistant
Classifier: Development Status :: 4 - Beta
Classifier: Intended Audience :: Developers
Classifier: Programming Language :: Python :: 3
Requires-Python: >=3.9.0
License-File: LICENSE
Requires-Dist: pyzipper>=0.3.6
Requires-Dist: striprtf>=0.0.26
